my_backend/__init__.py
my_backend/main.py
LENSE_STREAM-0.1.dist-info/METADATA
LENSE_STREAM-0.1.dist-info/WHEEL
LENSE_STREAM-0.1.dist-info/entry_points.txt
LENSE_STREAM-0.1.dist-info/top_level.txt
LENSE_STREAM-0.1.dist-info/RECORD
